<oai_dc:dc xmlns:oai_dc="http://www.openarchives.org/OAI/2.0/oai_dc/" xmlns:dc="http://purl.org/dc/elements/1.1/" xmlns:xsi="http://www.w3.org/2001/XMLSchema-instance" xsi:schemaLocation="http://www.openarchives.org/OAI/2.0/oai_dc/ http://www.openarchives.org/OAI/2.0/oai_dc.xsd">
  <dc:title>ICCOA – Indian Competence Centre for Organic Agriculture</dc:title>
  <dc:creator>Eyhorn, Frank</dc:creator>
  <dc:subject>Education, extension and communication</dc:subject>
  <dc:subject>Research communication and quality</dc:subject>
  <dc:subject>India</dc:subject>
  <dc:description>Contents of this presentation&#xD;
- Why Organic Agriculture in India? &#xD;
- Organic Production in India – in a nutshell&#xD;
- Collaboration with FiBL - The Research Institute of Organic Farming&#xD;
- Indo-Swiss Dialogue on Organic Agriculture&#xD;
- Analysis of the Organic Agriculture Sector in India&#xD;
- Planning Workshop in Delhi&#xD;
- Founding Board of DirectorsFields of Activities of ICCOA&#xD;
- Organisationnal Chart of ICCOAPlanned projects and mandates of ICCOA (examples)&#xD;
- What have we achieved so far?&#xD;
- Indian Organic Market Development Project Project Funding Options Ahead&#xD;
- Why your support is needed</dc:description>
  <dc:date>2004</dc:date>
  <dc:type>Other</dc:type>
  <dc:type>NonPeerReviewed</dc:type>
  <dc:format>application/pdf</dc:format>
  <dc:identifier>http://orgprints.org/2766/1/eyhorn-2004-ICCOA_Indian_Competence_Centre.pdf</dc:identifier>
  <dc:identifier>Eyhorn, Frank    (2004) ICCOA – Indian Competence Centre for Organic Agriculture.   Research Institute of Organic Agriculture, Frick, Switzerland, International Cooperation.   [Unpublished]</dc:identifier>
  <dc:relation>http://orgprints.org/2766/</dc:relation>
</oai_dc:dc>