<oai_dc:dc xmlns:oai_dc="http://www.openarchives.org/OAI/2.0/oai_dc/" xmlns:dc="http://purl.org/dc/elements/1.1/" xmlns:xsi="http://www.w3.org/2001/XMLSchema-instance" xsi:schemaLocation="http://www.openarchives.org/OAI/2.0/oai_dc/ http://www.openarchives.org/OAI/2.0/oai_dc.xsd">
  <dc:title>Tørket eller ensilert bygg til kyr i økologisk landbruk</dc:title>
  <dc:creator>Adler, Steffen A.</dc:creator>
  <dc:creator>Randby, Åshild T.</dc:creator>
  <dc:subject>Crop health, quality, protection</dc:subject>
  <dc:subject>Feeding and growth</dc:subject>
  <dc:description>Ensilert bygg ble sammenlignet med tørket bygg som eneste kraftfôr til melkekyr i økologisk landbruk. Melkeproduksjonen har vært moderat i gruppen med 40% kraftfôr og lav i gruppen med 10% kraftfôr. Både tørking og ensilering konserverte bygget godt, med antydning til mugg på toppen av sekker med det ensilerte. Begge fôrslag hadde omtrent samme virkning på fôropptak og produksjon. Det har vist seg at bygg alene er for lite smakelig når det gis større mengder. Proteininnholdet i bygg var for lavt når det ble gitt som eneste kraftfôr til et surfôr med lavt proteininnhold.</dc:description>
  <dc:contributor>Kaurstad, Elin Kristine</dc:contributor>
  <dc:date>2005</dc:date>
  <dc:type>Conference paper, poster, etc.</dc:type>
  <dc:type>NonPeerReviewed</dc:type>
  <dc:format>application/pdf</dc:format>
  <dc:identifier>http://orgprints.org/6422/1/HFM_2005_108.pdf</dc:identifier>
  <dc:identifier>Adler, Steffen A. and Randby, Åshild T.    (2005) Tørket eller ensilert bygg til kyr i økologisk landbruk.  [Dried or ensiled barley for cows in organic farming.]  In: Kaurstad, Elin Kristine (Ed.)  Husdyrforsøksmøtet 2005, pp. 427-430.</dc:identifier>
  <dc:relation>http://orgprints.org/6422/</dc:relation>
</oai_dc:dc>