<oai_dc:dc xmlns:oai_dc="http://www.openarchives.org/OAI/2.0/oai_dc/" xmlns:dc="http://purl.org/dc/elements/1.1/" xmlns:xsi="http://www.w3.org/2001/XMLSchema-instance" xsi:schemaLocation="http://www.openarchives.org/OAI/2.0/oai_dc/ http://www.openarchives.org/OAI/2.0/oai_dc.xsd">
  <dc:title>Proceedings of the Workshop on Organic Public Catering at the 16th IFOAM Organic World Congress, 19th June 2008 in Modena, Italy</dc:title>
  <dc:subject>Policy environments and social economy</dc:subject>
  <dc:subject>Food security, food quality and human health</dc:subject>
  <dc:subject>Food systems</dc:subject>
  <dc:subject>Markets and trade</dc:subject>
  <dc:subject>Consumer issues</dc:subject>
  <dc:subject>Produce chain management</dc:subject>
  <dc:description>This proceedings shows the papers and/or power point slides of presentations held during a workshop included in the OWC about how to include organic food in school meals in various countries in Europe and Asia. the workshop was arranged by the iPOPY project (more at www.ipopy.coreportal.org).</dc:description>
  <dc:publisher>ICROFS, Denmark</dc:publisher>
  <dc:contributor>Strassner, Carola</dc:contributor>
  <dc:contributor>Løes, Anne-Kristin</dc:contributor>
  <dc:contributor>Kristensen, Niels Heine</dc:contributor>
  <dc:contributor>Spigarolo, Roberto</dc:contributor>
  <dc:date>2009</dc:date>
  <dc:type>Proceedings</dc:type>
  <dc:type>NonPeerReviewed</dc:type>
  <dc:format>application/pdf</dc:format>
  <dc:identifier>http://orgprints.org/15203/1/OWC_Modena_2008_iPOPY_WS_proceedings_Strassner_et_al_CORE_series.pdf</dc:identifier>
  <dc:identifier>Strassner, Carola; Løes, Anne-Kristin; Kristensen, Niels Heine and Spigarolo, Roberto (Eds.)    (2009) Proceedings of the Workshop on Organic Public Catering at the 16th IFOAM Organic World Congress, 19th June 2008 in Modena, Italy.   ICROFS, Denmark, Core Organic Project Series Report.  Proceedings of Workshop on Organic Public Catering at the 16th IFOAM Organic World Congress, Modena, Italy, June 19, 2008.</dc:identifier>
  <dc:relation>http://orgprints.org/15203/</dc:relation>
</oai_dc:dc>