<oai_dc:dc xmlns:oai_dc="http://www.openarchives.org/OAI/2.0/oai_dc/" xmlns:dc="http://purl.org/dc/elements/1.1/" xmlns:xsi="http://www.w3.org/2001/XMLSchema-instance" xsi:schemaLocation="http://www.openarchives.org/OAI/2.0/oai_dc/ http://www.openarchives.org/OAI/2.0/oai_dc.xsd">
  <dc:title>Anleitung zur Nutzung der Datenbank „Organic Eprints“ (www.orgprints.org)</dc:title>
  <dc:creator>Meier, Julia</dc:creator>
  <dc:creator>Willer, Helga</dc:creator>
  <dc:creator>Gerlach, Florian</dc:creator>
  <dc:subject>Research communication and quality</dc:subject>
  <dc:description>1 Die Datenbank Organic Eprints&#xD;
2 Allgemeine Hinweise zur Nutzung der Datenbank Organic Eprints&#xD;
3 Warum Veröffentlichungen in Organic Eprints einstellen?&#xD;
4 Registrieren: Benutzerkonto bei Organic Eprints anlegen und Benutzerangaben eingeben&#xD;
5 Ihr Benutzerbereich&#xD;
5.1 Benutzerbereich aufrufen&#xD;
5.2 Benutzerangaben anschauen/ändern10&#xD;
5.3 E-Mail-Benachrichtigungsdienst abonnieren/ändern&#xD;
5.4 E-Mail-Adresse ändern&#xD;
5.5 Unter einem neuen Benutzernamen anmelden&#xD;
6 Dokumente in die Datenbank einstellen&#xD;
7 Kontakt</dc:description>
  <dc:date>2007-09</dc:date>
  <dc:type>Other</dc:type>
  <dc:type>NonPeerReviewed</dc:type>
  <dc:format>application/pdf</dc:format>
  <dc:identifier>http://orgprints.org/3296/1/forschung_orgprints-anleitung_070917_final.pdf</dc:identifier>
  <dc:identifier>Meier, Julia; Willer, Helga and Gerlach, Florian    (2007) Anleitung zur Nutzung der Datenbank „Organic Eprints“ (www.orgprints.org).  [Instructions for the use of the database "Organic Eprints".]  Forschungsinstitut für biologischen Landbau (FiBL Deutschland e.V.), D-Frankfurt am Main.   [Unpublished]</dc:identifier>
  <dc:relation>http://orgprints.org/3296/</dc:relation>
</oai_dc:dc>