<oai_dc:dc xmlns:oai_dc="http://www.openarchives.org/OAI/2.0/oai_dc/" xmlns:dc="http://purl.org/dc/elements/1.1/" xmlns:xsi="http://www.w3.org/2001/XMLSchema-instance" xsi:schemaLocation="http://www.openarchives.org/OAI/2.0/oai_dc/ http://www.openarchives.org/OAI/2.0/oai_dc.xsd">
  <dc:title>As perspectivas da pequena produção familiar na agricultura.</dc:title>
  <dc:creator>Ciprandi, Olivio</dc:creator>
  <dc:creator>Neto, João Fert</dc:creator>
  <dc:subject>Farming Systems</dc:subject>
  <dc:subject>Social aspects</dc:subject>
  <dc:description>As perspectivas da pequena produção familiar na agricultura constitui um tema controvertido na sociologia e na economia rural. A modernização da agricultura alterou suas relações com o restante da economia. As mudanças na base técnica e as políticas agrícolas determinaram a necessidade de crescimento das escalas mínimas viáveis do ponto de vista técnico e econômico, promovendo um processo de seleção e exclusão entre os pequenos produtores rurais, sem no entanto implicar na eliminação da pequena produção familiar.</dc:description>
  <dc:date>1996-01</dc:date>
  <dc:type>Journal paper</dc:type>
  <dc:type>NonPeerReviewed</dc:type>
  <dc:format>application/pdf</dc:format>
  <dc:identifier>http://orgprints.org/22655/1/Ciprandi_Perspectivas.pdf</dc:identifier>
  <dc:identifier>Ciprandi, Olivio  and Neto, João Fert    (1996) As perspectivas da pequena produção familiar na agricultura.  [The perspectives for the small familiar farming.]  Ciência Rural, 26 (1), pp. 135-141.</dc:identifier>
  <dc:relation>http://orgprints.org/22655/</dc:relation>
</oai_dc:dc>