<oai_dc:dc xmlns:oai_dc="http://www.openarchives.org/OAI/2.0/oai_dc/" xmlns:dc="http://purl.org/dc/elements/1.1/" xmlns:xsi="http://www.w3.org/2001/XMLSchema-instance" xsi:schemaLocation="http://www.openarchives.org/OAI/2.0/oai_dc/ http://www.openarchives.org/OAI/2.0/oai_dc.xsd">
  <dc:title>ENOAT – European Network of Organic Agriculture Teachers</dc:title>
  <dc:creator>von Fragstein und Niemsdorff, Prof. Dr. Peter</dc:creator>
  <dc:subject>Education, extension and communication</dc:subject>
  <dc:description>Curriculum development for organic agriculture was the initial point of an Erasmus&#xD;
group of 7 universities from 1995 till 1998. The expansion of EU member states&#xD;
coincided with the growing interest of further member states to become part of this&#xD;
informal group of university teachers. Since some years the group of meanwhile 23&#xD;
countries is named ENOAT and seeks to improve the inter university exchange of&#xD;
students and staff members, to encourage the dissemination and implementation of&#xD;
organic agriculture courses, to organize annual meeting including workshops on&#xD;
teaching methodology, and to organize summer courses on specific topics relevant for&#xD;
organic agriculture.</dc:description>
  <dc:date>2009</dc:date>
  <dc:type>Conference paper, poster, etc.</dc:type>
  <dc:type>NonPeerReviewed</dc:type>
  <dc:format>application/pdf</dc:format>
  <dc:identifier>http://orgprints.org/14515/1/FragsteinundNiemsdorff_14515.pdf</dc:identifier>
  <dc:identifier>von Fragstein und Niemsdorff, Prof. Dr. Peter    (2009) ENOAT – European Network of Organic Agriculture Teachers.       Paper at:   10. Wissenschaftstagung Ökologischer Landbau, Zürich, 11.-13. Februar 2009.</dc:identifier>
  <dc:relation>http://orgprints.org/14515/</dc:relation>
</oai_dc:dc>